modTable/__init__.py
modTable/__main__.py
modTable-2.0.1.dist-info/LICENSE
modTable-2.0.1.dist-info/METADATA
modTable-2.0.1.dist-info/WHEEL
modTable-2.0.1.dist-info/entry_points.txt
modTable-2.0.1.dist-info/top_level.txt
modTable-2.0.1.dist-info/RECORD
