Metadata-Version: 2.2
Name: modTable
Version: 2.0.1
Summary: Prints addition and multiplication tables for Z mod n*Z
Home-page: https://github.com/jrowellfx/modTable
Author: James Philip Rowell
Author-email: james@alpha-eleven.com
Classifier: Programming Language :: Python :: 3
Classifier: License :: OSI Approved :: BSD License
Classifier: Operating System :: POSIX
Classifier: Operating System :: Unix
Classifier: Operating System :: MacOS
Classifier: Development Status :: 5 - Production/Stable
Requires-Python: >=3.6, <4
License-File: LICENSE
Dynamic: author
Dynamic: author-email
Dynamic: classifier
Dynamic: description
Dynamic: description-content-type
Dynamic: home-page
Dynamic: requires-python
Dynamic: summary
